streamlit_gradio/__init__.py
streamlit_gradio/component.py
streamlit_gradio/encryptor.py
streamlit_gradio/external.py
streamlit_gradio/flagging.py
streamlit_gradio/inputs.py
streamlit_gradio/interface.py
streamlit_gradio/interpretation.py
streamlit_gradio/mix.py
streamlit_gradio/notebook.py
streamlit_gradio/outputs.py
streamlit_gradio/process_examples.py
streamlit_gradio/processing_utils.py
streamlit_gradio/streamlit_component.py
streamlit_gradio/test_data.py
streamlit_gradio/themes.py
streamlit_gradio/tunneling.py
streamlit_gradio/utils.py
streamlit_gradio/version.txt
streamlit_gradio/frontend/dist/index.html
streamlit_gradio/frontend/dist/assets/base.e4f5dae2.css
streamlit_gradio/frontend/dist/assets/clear.bf0a458a.svg
streamlit_gradio/frontend/dist/assets/default.aa9f0da0.css
streamlit_gradio/frontend/dist/assets/edit.82f21b4b.svg
streamlit_gradio/frontend/dist/assets/grass.003b092f.css
streamlit_gradio/frontend/dist/assets/huggingface.015b638f.css
streamlit_gradio/frontend/dist/assets/index.4709c7ef.js
streamlit_gradio/frontend/dist/assets/index.8c791f81.css
streamlit_gradio/frontend/dist/assets/peach.dfed2a06.css
streamlit_gradio/frontend/dist/assets/seafoam.b1fb20bd.css
streamlit_gradio-2.8.2.dist-info/LICENSE
streamlit_gradio-2.8.2.dist-info/METADATA
streamlit_gradio-2.8.2.dist-info/WHEEL
streamlit_gradio-2.8.2.dist-info/top_level.txt
streamlit_gradio-2.8.2.dist-info/RECORD
