Metadata-Version: 2.1
Name: streamlit-gradio
Version: 2.8.2
Summary: A streamlit wrapper for gradio
Home-page: https://github.com/truefoundry/streamlit-gradio
Author: Rishikesh Anand
Author-email: rishi1998@gmail.com
License: Apache License 2.0
Keywords: machine learning,visualization,reproducibility
Platform: UNKNOWN
License-File: LICENSE
